{"nodes": [{"id": "src_app_api_vendors_id_route_ts", "label": "route.ts", "file_type": "code", "source_file": "src\\app\\api\\vendors\\[id]\\route.ts", "source_location": "L1"}, {"id": "route_put", "label": "PUT()", "file_type": "code", "source_file": "src\\app\\api\\vendors\\[id]\\route.ts", "source_location": "L6"}], "edges": [{"source": "src_app_api_vendors_id_route_ts", "target": "src_server_api_responses_ts", "relation": "imports_from", "confidence": "EXTRACTED", "source_file": "src\\app\\api\\vendors\\[id]\\route.ts", "source_location": "L1", "weight": 1.0}, {"source": "src_app_api_vendors_id_route_ts", "target": "src_server_api_request_context_ts", "relation": "imports_from", "confidence": "EXTRACTED", "source_file": "src\\app\\api\\vendors\\[id]\\route.ts", "source_location": "L2", "weight": 1.0}, {"source": "src_app_api_vendors_id_route_ts", "target": "src_server_api_validation_ts", "relation": "imports_from", "confidence": "EXTRACTED", "source_file": "src\\app\\api\\vendors\\[id]\\route.ts", "source_location": "L3", "weight": 1.0}, {"source": "src_app_api_vendors_id_route_ts", "target": "src_server_services_master_data_master_data_ts", "relation": "imports_from", "confidence": "EXTRACTED", "source_file": "src\\app\\api\\vendors\\[id]\\route.ts", "source_location": "L4", "weight": 1.0}, {"source": "src_app_api_vendors_id_route_ts", "target": "route_put", "relation": "contains", "confidence": "EXTRACTED", "source_file": "src\\app\\api\\vendors\\[id]\\route.ts", "source_location": "L6", "weight": 1.0}], "raw_calls": [{"caller_nid": "route_put", "callee": "getRequestContext", "source_file": "src\\app\\api\\vendors\\[id]\\route.ts", "source_location": "L8"}, {"caller_nid": "route_put", "callee": "readJson", "source_file": "src\\app\\api\\vendors\\[id]\\route.ts", "source_location": "L9"}, {"caller_nid": "route_put", "callee": "updateVendor", "source_file": "src\\app\\api\\vendors\\[id]\\route.ts", "source_location": "L11"}, {"caller_nid": "route_put", "callee": "stringField", "source_file": "src\\app\\api\\vendors\\[id]\\route.ts", "source_location": "L12"}, {"caller_nid": "route_put", "callee": "stringField", "source_file": "src\\app\\api\\vendors\\[id]\\route.ts", "source_location": "L13"}, {"caller_nid": "route_put", "callee": "optionalStringField", "source_file": "src\\app\\api\\vendors\\[id]\\route.ts", "source_location": "L14"}, {"caller_nid": "route_put", "callee": "optionalStringField", "source_file": "src\\app\\api\\vendors\\[id]\\route.ts", "source_location": "L15"}, {"caller_nid": "route_put", "callee": "optionalStringField", "source_file": "src\\app\\api\\vendors\\[id]\\route.ts", "source_location": "L16"}, {"caller_nid": "route_put", "callee": "optionalStringField", "source_file": "src\\app\\api\\vendors\\[id]\\route.ts", "source_location": "L17"}, {"caller_nid": "route_put", "callee": "ok", "source_file": "src\\app\\api\\vendors\\[id]\\route.ts", "source_location": "L19"}, {"caller_nid": "route_put", "callee": "includes", "source_file": "src\\app\\api\\vendors\\[id]\\route.ts", "source_location": "L21"}, {"caller_nid": "route_put", "callee": "fail", "source_file": "src\\app\\api\\vendors\\[id]\\route.ts", "source_location": "L21"}, {"caller_nid": "route_put", "callee": "serviceError", "source_file": "src\\app\\api\\vendors\\[id]\\route.ts", "source_location": "L21"}]}