{"nodes": [{"id": "src_app_api_rbac_permissions_route_ts", "label": "route.ts", "file_type": "code", "source_file": "src\\app\\api\\rbac\\permissions\\route.ts", "source_location": "L1"}, {"id": "route_get", "label": "GET()", "file_type": "code", "source_file": "src\\app\\api\\rbac\\permissions\\route.ts", "source_location": "L6"}], "edges": [{"source": "src_app_api_rbac_permissions_route_ts", "target": "src_server_api_request_context_ts", "relation": "imports_from", "confidence": "EXTRACTED", "source_file": "src\\app\\api\\rbac\\permissions\\route.ts", "source_location": "L1", "weight": 1.0}, {"source": "src_app_api_rbac_permissions_route_ts", "target": "src_server_api_responses_ts", "relation": "imports_from", "confidence": "EXTRACTED", "source_file": "src\\app\\api\\rbac\\permissions\\route.ts", "source_location": "L2", "weight": 1.0}, {"source": "src_app_api_rbac_permissions_route_ts", "target": "src_server_services_rbac_permissions_ts", "relation": "imports_from", "confidence": "EXTRACTED", "source_file": "src\\app\\api\\rbac\\permissions\\route.ts", "source_location": "L3", "weight": 1.0}, {"source": "src_app_api_rbac_permissions_route_ts", "target": "src_server_services_rbac_role_management_ts", "relation": "imports_from", "confidence": "EXTRACTED", "source_file": "src\\app\\api\\rbac\\permissions\\route.ts", "source_location": "L4", "weight": 1.0}, {"source": "src_app_api_rbac_permissions_route_ts", "target": "route_get", "relation": "contains", "confidence": "EXTRACTED", "source_file": "src\\app\\api\\rbac\\permissions\\route.ts", "source_location": "L6", "weight": 1.0}], "raw_calls": [{"caller_nid": "route_get", "callee": "getRequestContext", "source_file": "src\\app\\api\\rbac\\permissions\\route.ts", "source_location": "L8"}, {"caller_nid": "route_get", "callee": "all", "source_file": "src\\app\\api\\rbac\\permissions\\route.ts", "source_location": "L9"}, {"caller_nid": "route_get", "callee": "listPermissions", "source_file": "src\\app\\api\\rbac\\permissions\\route.ts", "source_location": "L9"}, {"caller_nid": "route_get", "callee": "getUserPermissionKeys", "source_file": "src\\app\\api\\rbac\\permissions\\route.ts", "source_location": "L9"}, {"caller_nid": "route_get", "callee": "ok", "source_file": "src\\app\\api\\rbac\\permissions\\route.ts", "source_location": "L10"}, {"caller_nid": "route_get", "callee": "serviceError", "source_file": "src\\app\\api\\rbac\\permissions\\route.ts", "source_location": "L12"}]}